pyan_unused_functions/__init__.py
pyan_unused_functions/analyzer.py
pyan_unused_functions/cli.py
pyan_unused_functions-0.1.2.dist-info/licenses/LICENSE
pyan_unused_functions-0.1.2.dist-info/METADATA
pyan_unused_functions-0.1.2.dist-info/WHEEL
pyan_unused_functions-0.1.2.dist-info/entry_points.txt
pyan_unused_functions-0.1.2.dist-info/top_level.txt
pyan_unused_functions-0.1.2.dist-info/RECORD
