Metadata-Version: 2.4
Name: pyan-unused-functions
Version: 0.1.2
Summary: Find unused functions in Python codebases - perfect for CLI usage and CI/CD pipelines
Home-page: https://github.com/yourusername/pyan-unused-functions
Author: Your Name
Author-email: mhs <mohammedhs404@gmail.com>
License: MIT
Project-URL: Homepage, https://github.com/MohammedHS404/pyan-unused-functions
Project-URL: Bug Tracker, https://github.com/MohammedHS404/pyan-unused-functions/issues
Keywords: static-analysis,code-quality,unused-code,linter,ast,dead-code,code-cleanup,ci-cd,github-actions,cli-tool,python-analysis,code-maintenance
Classifier: Development Status :: 4 - Beta
Classifier: Intended Audience :: Developers
Classifier: License :: OSI Approved :: MIT License
Classifier: Programming Language :: Python :: 3
Classifier: Programming Language :: Python :: 3.7
Classifier: Programming Language :: Python :: 3.8
Classifier: Programming Language :: Python :: 3.9
Classifier: Programming Language :: Python :: 3.10
Classifier: Programming Language :: Python :: 3.11
Classifier: Programming Language :: Python :: 3.12
Classifier: Topic :: Software Development :: Quality Assurance
Classifier: Topic :: Software Development :: Libraries :: Python Modules
Requires-Python: >=3.7
License-File: LICENSE
Requires-Dist: pyan3==1.1.1
Dynamic: author
Dynamic: home-page
Dynamic: license-file
Dynamic: requires-python
